wf2wf/__init__.py
wf2wf/__main__.py
wf2wf/cli.py
wf2wf/config.py
wf2wf/core.py
wf2wf/environ.py
wf2wf/environment_adaptation.py
wf2wf/expression.py
wf2wf/interactive.py
wf2wf/loss.py
wf2wf/prompt.py
wf2wf/report.py
wf2wf/resource_utils.py
wf2wf/scatter.py
wf2wf/validate.py
wf2wf/workflow_analysis.py
wf2wf/adaptation/__init__.py
wf2wf/adaptation/base.py
wf2wf/adaptation/environments.py
wf2wf/adaptation/logging.py
wf2wf/adaptation/registry.py
wf2wf/adaptation/resources.py
wf2wf/adaptation/utils.py
wf2wf/adaptation/strategies/__init__.py
wf2wf/adaptation/strategies/shared_to_cloud.py
wf2wf/adaptation/strategies/shared_to_distributed.py
wf2wf/exporters/__init__.py
wf2wf/exporters/base.py
wf2wf/exporters/bco.py
wf2wf/exporters/cwl.py
wf2wf/exporters/dagman.py
wf2wf/exporters/galaxy.py
wf2wf/exporters/inference.py
wf2wf/exporters/nextflow.py
wf2wf/exporters/snakemake.py
wf2wf/exporters/wdl.py
wf2wf/importers/__init__.py
wf2wf/importers/base.py
wf2wf/importers/cwl.py
wf2wf/importers/dagman.py
wf2wf/importers/galaxy.py
wf2wf/importers/inference.py
wf2wf/importers/nextflow.py
wf2wf/importers/resource_processor.py
wf2wf/importers/snakemake.py
wf2wf/importers/utils.py
wf2wf/importers/wdl.py
wf2wf/loss/__init__.py
wf2wf/loss/context_detection.py
wf2wf/loss/core.py
wf2wf/loss/export.py
wf2wf/loss/import_.py
wf2wf/schemas/v0.1/loss.json
wf2wf/schemas/v0.1/wf.json
wf2wf/utils/format_detection.py
wf2wf-1.1.0.dist-info/licenses/LICENSE
wf2wf-1.1.0.dist-info/METADATA
wf2wf-1.1.0.dist-info/WHEEL
wf2wf-1.1.0.dist-info/entry_points.txt
wf2wf-1.1.0.dist-info/top_level.txt
wf2wf-1.1.0.dist-info/RECORD
