Metadata-Version: 2.4
Name: wf2wf
Version: 1.1.0
Summary: Universal workflow-format converter built around a loss-preserving intermediate representation
Author-email: wf2wf contributors <maintainers@wf2wf.dev>
License: MIT
Project-URL: Homepage, https://csmcal.github.io/wf2wf/
Project-URL: Documentation, https://csmcal.github.io/wf2wf/
Project-URL: Repository, https://github.com/csmcal/wf2wf
Project-URL: Issues, https://github.com/csmcal/wf2wf/issues
Project-URL: Changelog, https://github.com/csmcal/wf2wf/blob/main/CHANGELOG.md
Keywords: workflow,cwl,snakemake,htcondor,dagman,nextflow,wdl,bioinformatics
Classifier: Programming Language :: Python :: 3
Classifier: Programming Language :: Python :: 3 :: Only
Classifier: Programming Language :: Python :: 3.9
Classifier: Programming Language :: Python :: 3.10
Classifier: Programming Language :: Python :: 3.11
Classifier: Programming Language :: Python :: 3.12
Classifier: Intended Audience :: Science/Research
Classifier: Topic :: Scientific/Engineering :: Bio-Informatics
Requires-Python: >=3.9
License-File: LICENSE
Requires-Dist: click>=8.1
Requires-Dist: jsonschema>=4
Requires-Dist: pyyaml>=6
Requires-Dist: markdown>=3.5; extra == "html"
Provides-Extra: dev
Requires-Dist: pytest>=8; extra == "dev"
Requires-Dist: pytest-cov; extra == "dev"
Requires-Dist: pre-commit; extra == "dev"
Requires-Dist: ruff; extra == "dev"
Requires-Dist: bumpver; extra == "dev"
Requires-Dist: snakemake>=7.32; extra == "dev"
Provides-Extra: html
Requires-Dist: markdown>=3.5; extra == "html"
Provides-Extra: docs
Requires-Dist: sphinx>=7; extra == "docs"
Requires-Dist: furo>=2023.9.10; extra == "docs"
Requires-Dist: myst-parser>=2; extra == "docs"
Requires-Dist: sphinx-click>=5; extra == "docs"
Dynamic: license-file
